[
    {
        "id": 1,
        "username": "Luke",
        "email": "lmgabel@gmail.com",
        "height": 73.0,
        "weight": 152.0,
        "password": "$2a$12$dRENtDbi1.2IipAsc6IaK.APWd/b5ND6Qt1UtX/Tnd9SRk38Qx/rm",
        "color": "#80ceff",
        "admin": 1,
        "group_link": null,
        "comps": "[3, 4, 5, 6, 7]",
        "friends": "[1, 4, 5, 6, 7, 8, 10, 2, 3]"
    },
    {
        "id": 2,
        "username": "DuBose",
        "email": "wpdtjr@gmail.com",
        "height": 71.0,
        "weight": 155.0,
        "password": "$2a$12$34IsVDERdCXfxZSNXQhpL.nNj9EANazO8asI9YkdaBl8hkz4V8hOy",
        "color": "#b6d7a8",
        "admin": 1,
        "group_link": null,
        "comps": "[3, 4, 6, 7]",
        "friends": "[2]"
    },
    {
        "id": 3,
        "username": "Sydney Helms",
        "email": "helmss9@mailbox.winthrop.edu",
        "height": 64.0,
        "weight": 110.0,
        "password": "$2a$12$f8O3WjuRmAVaGmPpfVzJnufF8AEiuHWJBuPs.yjbndbbsZXp.6LLy",
        "color": "#ff8280",
        "admin": 0,
        "group_link": null,
        "comps": "[3, 4, 6, 7]",
        "friends": "[1, 2, 4, 5, 6, 7, 3, 10, 8]"
    },
    {
        "id": 4,
        "username": "Molly Caballero",
        "email": "mollycaballero02@gmail.com",
        "height": 64.0,
        "weight": 132.0,
        "password": "$2a$12$p3I0RiIYFWSVUzHorY2iguaOSxp3ZdvLYDBJinQ4g7qxm/eXw4HDu",
        "color": "#808eff",
        "admin": 0,
        "group_link": null,
        "comps": "[3, 4, 6, 7]",
        "friends": "[4]"
    },
    {
        "id": 5,
        "username": "Andrew",
        "email": "ajsobel2@gmail.com",
        "height": 75.0,
        "weight": 166.0,
        "password": "$2a$12$Za1lM3x/h2TuLalgHSGG9O3EOKGau5Q4qQcJ7OKfc.rou/I3b.Z02",
        "color": "#ff80ec",
        "admin": 1,
        "group_link": null,
        "comps": "[3, 4, 5, 6, 7]",
        "friends": "[1, 2, 3, 4, 5, 6, 7, 8, 9, 10]"
    },
    {
        "id": 6,
        "username": "Caroline",
        "email": "20cwquan@gmail.com",
        "height": 62.0,
        "weight": 115.0,
        "password": "$2a$12$wu.ZNQ1MY5sK1c8Ev2rtN.MvKltGe5/P1tVuFp3H9s.qCfrAvLl02",
        "color": "#f9ff80",
        "admin": 0,
        "group_link": null,
        "comps": "[3, 4, 6, 7]",
        "friends": "[6]"
    },
    {
        "id": 7,
        "username": "Ava Rosenbaum",
        "email": "avagrace467@gmail.com",
        "height": 66.0,
        "weight": 140.0,
        "password": "$2a$12$g12fXIB/Se/6JE2usewZSel1uVc3FWZ.XiVH3ctXc0g3OvrTc9K.2",
        "color": "#ff80f9",
        "admin": 0,
        "group_link": null,
        "comps": "[3, 4, 6, 7]",
        "friends": "[7, 1, 2, 3, 4, 5, 6, 9, 8, 10]"
    },
    {
        "id": 8,
        "username": "Amelia",
        "email": "ameliandujar25@gmail.com",
        "height": 59.0,
        "weight": 120.0,
        "password": "$2a$12$TRAWXZ7t8/.2OpDavC4BDOknpQdFKGQ/viiCUhkX4cPCOqfZgSONu",
        "color": "#ffce80",
        "admin": 0,
        "group_link": null,
        "comps": "[3, 4, 6, 7]",
        "friends": "[8]"
    },
    {
        "id": 9,
        "username": "Chloe Rosenbaum",
        "email": "chloebaum9@gmail.com",
        "height": 60.0,
        "weight": 87.0,
        "password": "$2a$12$4vkjB8AauSX3QpEnp2SOsOjNv/N9tC9PZJaZckrbWR7Vx2M2MsOha",
        "color": "#d8f283",
        "admin": 0,
        "group_link": null,
        "comps": "[3, 6]",
        "friends": "[9]"
    },
    {
        "id": 10,
        "username": "Olivia",
        "email": "oantonetti16@gmail.com",
        "height": 67.0,
        "weight": 120.0,
        "password": "$2a$12$Uz3y3r97Ody5uJKFJ67L5.0CyKv8ikCGGBQIqRaxpw97q0YsC82oC",
        "color": "#ff80b5",
        "admin": 0,
        "group_link": null,
        "comps": "[3, 4, 6, 7]",
        "friends": "[10]"
    }
]